openhands/agent_server/__init__.py
openhands/agent_server/__main__.py
openhands/agent_server/api.py
openhands/agent_server/bash_router.py
openhands/agent_server/bash_service.py
openhands/agent_server/config.py
openhands/agent_server/conversation_router.py
openhands/agent_server/conversation_service.py
openhands/agent_server/dependencies.py
openhands/agent_server/desktop_router.py
openhands/agent_server/desktop_service.py
openhands/agent_server/env_parser.py
openhands/agent_server/event_router.py
openhands/agent_server/event_service.py
openhands/agent_server/file_router.py
openhands/agent_server/git_router.py
openhands/agent_server/logging_config.py
openhands/agent_server/middleware.py
openhands/agent_server/models.py
openhands/agent_server/openapi.py
openhands/agent_server/pub_sub.py
openhands/agent_server/py.typed
openhands/agent_server/server_details_router.py
openhands/agent_server/skills_router.py
openhands/agent_server/skills_service.py
openhands/agent_server/sockets.py
openhands/agent_server/tool_preload_service.py
openhands/agent_server/tool_router.py
openhands/agent_server/utils.py
openhands/agent_server/vscode_router.py
openhands/agent_server/vscode_service.py
openhands/agent_server/docker/Dockerfile
openhands/agent_server/docker/build.py
openhands/agent_server/docker/wallpaper.svg
openhands/agent_server/vscode_extensions/openhands-settings/extension.js
openhands/agent_server/vscode_extensions/openhands-settings/package.json
openhands_agent_server-1.10.0.dist-info/METADATA
openhands_agent_server-1.10.0.dist-info/WHEEL
openhands_agent_server-1.10.0.dist-info/entry_points.txt
openhands_agent_server-1.10.0.dist-info/top_level.txt
openhands_agent_server-1.10.0.dist-info/RECORD
